triangulate/__init__.py
triangulate/ast_utils.py
triangulate/core.py
triangulate/instrumentation_utils.py
triangulate/logging_utils.py
triangulate/main.py
triangulate/sampling_utils.py
triangulate/testdata/__init__.py
triangulate/testdata/multistep.py
triangulate/testdata/quoter.py
triangulate/testdata/multifile_example/__init__.py
triangulate/testdata/multifile_example/library_a.py
triangulate/testdata/multifile_example/library_b.py
triangulate/testdata/multifile_example/main.py
triangulate-0.1.0.dist-info/LICENSE
triangulate-0.1.0.dist-info/WHEEL
triangulate-0.1.0.dist-info/METADATA
triangulate-0.1.0.dist-info/RECORD
