Metadata-Version: 2.1
Name: triangulate
Version: 0.1.0
Summary: Bug localization by reinforcement learning
Keywords: 
Author-email: triangulate authors <triangulate-automated@google.com>
Requires-Python: >=3.10
Classifier: License :: OSI Approved :: Apache Software License
Classifier: Intended Audience :: Science/Research
Requires-Dist: absl-py
Requires-Dist: numpy
Requires-Dist: rich
Requires-Dist: python-magic
Requires-Dist: pytest ; extra == "dev"
Requires-Dist: pytest-xdist ; extra == "dev"
Requires-Dist: pylint>=2.6.0 ; extra == "dev"
Requires-Dist: pytype ; extra == "dev"
Requires-Dist: pyink ; extra == "dev"
Project-URL: changelog, https://github.com/google-research/triangulate/blob/main/CHANGELOG.md
Project-URL: homepage, https://github.com/google-research/triangulate
Project-URL: repository, https://github.com/google-research/triangulate
Provides-Extra: dev
